odoo/addons/account_invoice_fixed_discount/README.rst
odoo/addons/account_invoice_fixed_discount/__init__.py
odoo/addons/account_invoice_fixed_discount/__manifest__.py
odoo/addons/account_invoice_fixed_discount/i18n/account_invoice_fixed_discount.pot
odoo/addons/account_invoice_fixed_discount/i18n/ca.po
odoo/addons/account_invoice_fixed_discount/i18n/de.po
odoo/addons/account_invoice_fixed_discount/i18n/es.po
odoo/addons/account_invoice_fixed_discount/i18n/it.po
odoo/addons/account_invoice_fixed_discount/models/__init__.py
odoo/addons/account_invoice_fixed_discount/models/account_move.py
odoo/addons/account_invoice_fixed_discount/readme/CONTRIBUTORS.rst
odoo/addons/account_invoice_fixed_discount/readme/DESCRIPTION.rst
odoo/addons/account_invoice_fixed_discount/readme/INSTALL.rst
odoo/addons/account_invoice_fixed_discount/readme/ROADMAP.rst
odoo/addons/account_invoice_fixed_discount/readme/USAGE.rst
odoo/addons/account_invoice_fixed_discount/reports/report_account_invoice.xml
odoo/addons/account_invoice_fixed_discount/static/description/icon.png
odoo/addons/account_invoice_fixed_discount/static/description/index.html
odoo/addons/account_invoice_fixed_discount/tests/__init__.py
odoo/addons/account_invoice_fixed_discount/tests/test_account_fixed_discount.py
odoo/addons/account_invoice_fixed_discount/views/account_move_view.xml
odoo14_addon_account_invoice_fixed_discount-14.0.1.0.4.dist-info/METADATA
odoo14_addon_account_invoice_fixed_discount-14.0.1.0.4.dist-info/WHEEL
odoo14_addon_account_invoice_fixed_discount-14.0.1.0.4.dist-info/top_level.txt
odoo14_addon_account_invoice_fixed_discount-14.0.1.0.4.dist-info/RECORD
